follow_up_boss/__init__.py
follow_up_boss/action_plans.py
follow_up_boss/appointment_outcomes.py
follow_up_boss/appointment_types.py
follow_up_boss/appointments.py
follow_up_boss/calls.py
follow_up_boss/client.py
follow_up_boss/custom_fields.py
follow_up_boss/deal_attachments.py
follow_up_boss/deal_custom_fields.py
follow_up_boss/deals.py
follow_up_boss/email_marketing.py
follow_up_boss/email_templates.py
follow_up_boss/enhanced_client.py
follow_up_boss/enhanced_people.py
follow_up_boss/events.py
follow_up_boss/groups.py
follow_up_boss/identity.py
follow_up_boss/inbox_apps.py
follow_up_boss/mcp_server.py
follow_up_boss/notes.py
follow_up_boss/pagination.py
follow_up_boss/people.py
follow_up_boss/people_relationships.py
follow_up_boss/person_attachments.py
follow_up_boss/pipelines.py
follow_up_boss/ponds.py
follow_up_boss/reactions.py
follow_up_boss/smart_lists.py
follow_up_boss/stages.py
follow_up_boss/tasks.py
follow_up_boss/team_inboxes.py
follow_up_boss/teams.py
follow_up_boss/text_message_templates.py
follow_up_boss/text_messages.py
follow_up_boss/threaded_replies.py
follow_up_boss/timeframes.py
follow_up_boss/users.py
follow_up_boss/webhook_events.py
follow_up_boss/webhooks.py
follow_up_boss-0.2.10.dist-info/licenses/LICENSE
follow_up_boss-0.2.10.dist-info/METADATA
follow_up_boss-0.2.10.dist-info/WHEEL
follow_up_boss-0.2.10.dist-info/entry_points.txt
follow_up_boss-0.2.10.dist-info/top_level.txt
follow_up_boss-0.2.10.dist-info/RECORD
