Metadata-Version: 2.4
Name: follow-up-boss
Version: 0.2.10
Summary: A Python client library for the Follow Up Boss API
Author-email: The Perry Group <contact@theperry.group>
License: MIT
Project-URL: Homepage, https://github.com/theperrygroup/follow-up-boss
Project-URL: Repository, https://github.com/theperrygroup/follow-up-boss
Project-URL: Documentation, https://github.com/theperrygroup/follow-up-boss#readme
Project-URL: Bug Tracker, https://github.com/theperrygroup/follow-up-boss/issues
Keywords: followupboss,api,client,real-estate,crm
Classifier: Development Status :: 4 - Beta
Classifier: Intended Audience :: Developers
Classifier: License :: OSI Approved :: MIT License
Classifier: Operating System :: OS Independent
Classifier: Programming Language :: Python :: 3
Classifier: Programming Language :: Python :: 3.8
Classifier: Programming Language :: Python :: 3.9
Classifier: Programming Language :: Python :: 3.10
Classifier: Programming Language :: Python :: 3.11
Classifier: Programming Language :: Python :: 3.12
Classifier: Topic :: Software Development :: Libraries :: Python Modules
Classifier: Topic :: Office/Business
Requires-Python: >=3.8
License-File: LICENSE
Requires-Dist: requests>=2.25.0
Requires-Dist: python-dotenv>=0.19.0
Provides-Extra: dev
Requires-Dist: pytest>=7.0.0; extra == "dev"
Requires-Dist: pytest-cov>=4.0.0; extra == "dev"
Requires-Dist: black>=22.0.0; extra == "dev"
Requires-Dist: isort>=5.10.0; extra == "dev"
Requires-Dist: mypy>=0.991; extra == "dev"
Requires-Dist: flake8>=5.0.0; extra == "dev"
Requires-Dist: pylint>=2.15.0; extra == "dev"
Requires-Dist: types-requests>=2.28.0; extra == "dev"
Provides-Extra: mcp
Requires-Dist: fastmcp>=0.1.0; extra == "mcp"
Requires-Dist: pydantic>=2.0.0; extra == "mcp"
Requires-Dist: uvloop>=0.19.0; extra == "mcp"
Dynamic: license-file
